<Collection>
  <product>
    <id>441488344</id>
    <name>Bowl</name>
    <coordinates>
      <coordinatesX>23</coordinatesX>
      <coordinatesY>201</coordinatesY>
    </coordinates>
    <creationDate>2022-04-03</creationDate>
    <price>329.0</price>
    <partNumber>7345617</partNumber>
    <manufactureCost>21</manufactureCost>
    <unitOfMeasure>MILLIGRAMS</unitOfMeasure>
    <person>
      <name>Hufflepuff</name>
      <passportID>923555737</passportID>
      <eyeColor>BROWN</eyeColor>
      <hairColor>YELLOW</hairColor>
      <country>ITALY</country>
      <location>
        <locationX>10.0</locationX>
        <locationY>1.2</locationY>
        <locationZ>23.0</locationZ>
      </location>
    </person>
  </product>
  <product>
    <id>1439700657</id>
    <name>Diadem</name>
    <coordinates>
      <coordinatesX>23</coordinatesX>
      <coordinatesY>201</coordinatesY>
    </coordinates>
    <creationDate>2022-04-03</creationDate>
    <price>12.0</price>
    <partNumber>2908</partNumber>
    <manufactureCost>45</manufactureCost>
    <unitOfMeasure>MILLIGRAMS</unitOfMeasure>
    <person>
      <name>Ravenclaw</name>
      <passportID>57977102</passportID>
      <eyeColor>BLUE</eyeColor>
      <hairColor>BLUE</hairColor>
      <country>FRANCE</country>
      <location>
        <locationX>10.0</locationX>
        <locationY>1.2</locationY>
        <locationZ>23.0</locationZ>
      </location>
    </person>
  </product>
  <product>
    <id>1861996133</id>
    <name>Diary</name>
    <coordinates>
      <coordinatesX>23</coordinatesX>
      <coordinatesY>201</coordinatesY>
    </coordinates>
    <creationDate>2022-04-03</creationDate>
    <price>3.0</price>
    <partNumber>263517</partNumber>
    <manufactureCost>40</manufactureCost>
    <unitOfMeasure>MILLIGRAMS</unitOfMeasure>
    <person>
      <name>Voldemort</name>
      <passportID>1906222446</passportID>
      <eyeColor>BROWN</eyeColor>
      <hairColor>BLACK</hairColor>
      <country>FRANCE</country>
      <location>
        <locationX>10.0</locationX>
        <locationY>1.2</locationY>
        <locationZ>23.0</locationZ>
      </location>
    </person>
  </product>
  <product>
    <id>705771319</id>
    <name>Medallion</name>
    <coordinates>
      <coordinatesX>23</coordinatesX>
      <coordinatesY>201</coordinatesY>
    </coordinates>
    <creationDate>2022-04-03</creationDate>
    <price>62473.0</price>
    <partNumber>439498</partNumber>
    <manufactureCost>76</manufactureCost>
    <unitOfMeasure>MILLIGRAMS</unitOfMeasure>
    <person>
      <name>Slytherin</name>
      <passportID>1726286874</passportID>
      <eyeColor>GREEN</eyeColor>
      <hairColor>BROWN</hairColor>
      <country>FRANCE</country>
      <location>
        <locationX>10.0</locationX>
        <locationY>1.2</locationY>
        <locationZ>23.0</locationZ>
      </location>
    </person>
  </product>
  <product>
    <id>1083714998</id>
    <name>Nagini</name>
    <coordinates>
      <coordinatesX>23</coordinatesX>
      <coordinatesY>201</coordinatesY>
    </coordinates>
    <creationDate>2022-04-03</creationDate>
    <price>27.0</price>
    <partNumber>10149</partNumber>
    <manufactureCost>100</manufactureCost>
    <unitOfMeasure>MILLIGRAMS</unitOfMeasure>
    <person>
      <name>Voldemort</name>
      <passportID>74565222</passportID>
      <eyeColor>BROWN</eyeColor>
      <hairColor>BLACK</hairColor>
      <country>FRANCE</country>
      <location>
        <locationX>10.0</locationX>
        <locationY>1.2</locationY>
        <locationZ>23.0</locationZ>
      </location>
    </person>
  </product>
  <product>
    <id>2132029886</id>
    <name>Potter</name>
    <coordinates>
      <coordinatesX>23</coordinatesX>
      <coordinatesY>201</coordinatesY>
    </coordinates>
    <creationDate>2022-04-03</creationDate>
    <price>877.0</price>
    <partNumber>149</partNumber>
    <manufactureCost>39</manufactureCost>
    <unitOfMeasure>CENTIMETERS</unitOfMeasure>
    <person>
      <name>Malfoy</name>
      <passportID>1190273873</passportID>
      <eyeColor>BLUE</eyeColor>
      <hairColor>YELLOW</hairColor>
      <country>ITALY</country>
      <location>
        <locationX>10.0</locationX>
        <locationY>1.2</locationY>
        <locationZ>23.0</locationZ>
      </location>
    </person>
  </product>
  <product>
    <id>992831284</id>
    <name>Ring</name>
    <coordinates>
      <coordinatesX>23</coordinatesX>
      <coordinatesY>201</coordinatesY>
    </coordinates>
    <creationDate>2022-04-03</creationDate>
    <price>1.12</price>
    <partNumber>26248</partNumber>
    <manufactureCost>25</manufactureCost>
    <unitOfMeasure>MILLIGRAMS</unitOfMeasure>
    <person>
      <name>Marvolo</name>
      <passportID>994978565</passportID>
      <eyeColor>GREEN</eyeColor>
      <hairColor>BLACK</hairColor>
      <country>INDIA</country>
      <location>
        <locationX>10.0</locationX>
        <locationY>1.2</locationY>
        <locationZ>23.0</locationZ>
      </location>
    </person>
  </product>
</Collection>